reponetwork/GithubCrawler.py
reponetwork/GitlabCrawler.py
reponetwork/__init__.py
reponetwork/repos.py
reponetwork-1.1.0.dist-info/LICENSE
reponetwork-1.1.0.dist-info/METADATA
reponetwork-1.1.0.dist-info/WHEEL
reponetwork-1.1.0.dist-info/entry_points.txt
reponetwork-1.1.0.dist-info/top_level.txt
reponetwork-1.1.0.dist-info/RECORD
