Metadata-Version: 2.1
Name: reponetwork
Version: 1.1.0
Summary: A network analysis tool for project repositories.
Home-page: https://github.com/ALabrada/PyRepos/
Author: Alexei Labrada Tsoraeva
Author-email: labrada.alexei@gmail.com
License: UNKNOWN
Platform: UNKNOWN
Classifier: Programming Language :: Python :: 3
Classifier: License :: OSI Approved :: MIT License
Classifier: Operating System :: OS Independent
Requires-Dist: PyGithub
Requires-Dist: python-gitlab
Requires-Dist: networkx
Requires-Dist: Matplotlib
Requires-Dist: wxPython
